instancepedia-0.2.0.dist-info/licenses/LICENSE
src/__init__.py
src/app.py
src/debug.py
src/main.py
src/cli/__init__.py
src/cli/commands.py
src/cli/output.py
src/cli/parser.py
src/config/__init__.py
src/config/settings.py
src/models/__init__.py
src/models/free_tier.py
src/models/instance_type.py
src/models/region.py
src/services/__init__.py
src/services/aws_client.py
src/services/free_tier_service.py
src/services/instance_service.py
src/services/pricing_service.py
src/ui/__init__.py
src/ui/instance_detail.py
src/ui/instance_list.py
src/ui/region_selector.py
instancepedia-0.2.0.dist-info/METADATA
instancepedia-0.2.0.dist-info/WHEEL
instancepedia-0.2.0.dist-info/entry_points.txt
instancepedia-0.2.0.dist-info/top_level.txt
instancepedia-0.2.0.dist-info/RECORD
