Metadata-Version: 2.4
Name: instancepedia
Version: 0.2.0
Summary: EC2 Instance Type Browser - TUI and CLI
Author: Paul Frederiksen
License: MIT
Project-URL: Homepage, https://github.com/pfrederiksen/instancepedia
Project-URL: Documentation, https://github.com/pfrederiksen/instancepedia#readme
Project-URL: Repository, https://github.com/pfrederiksen/instancepedia
Project-URL: Issues, https://github.com/pfrederiksen/instancepedia/issues
Keywords: aws,ec2,instance-types,tui,terminal,cli,pricing,cloud,textual
Classifier: Development Status :: 4 - Beta
Classifier: Intended Audience :: Developers
Classifier: Intended Audience :: System Administrators
Classifier: License :: OSI Approved :: MIT License
Classifier: Operating System :: OS Independent
Classifier: Programming Language :: Python :: 3
Classifier: Programming Language :: Python :: 3.8
Classifier: Programming Language :: Python :: 3.9
Classifier: Programming Language :: Python :: 3.10
Classifier: Programming Language :: Python :: 3.11
Classifier: Programming Language :: Python :: 3.12
Classifier: Topic :: System :: Systems Administration
Classifier: Topic :: Utilities
Classifier: Topic :: Software Development :: Libraries :: Python Modules
Classifier: Environment :: Console
Classifier: Environment :: Console :: Curses
Requires-Python: >=3.8
License-File: LICENSE
Requires-Dist: textual>=0.40.0
Requires-Dist: boto3>=1.28.0
Requires-Dist: pydantic>=2.0.0
Requires-Dist: pydantic-settings>=2.0.0
Requires-Dist: tabulate>=0.9.0
Provides-Extra: dev
Requires-Dist: build>=0.10.0; extra == "dev"
Requires-Dist: twine>=4.0.0; extra == "dev"
Requires-Dist: pytest>=7.0.0; extra == "dev"
Dynamic: license-file
